scrapy_sessions/__init__.py
scrapy_sessions/middleware.py
scrapy_sessions/objects.py
scrapy_sessions/utils.py
scrapy_sessions-0.9.dist-info/LICENSE
scrapy_sessions-0.9.dist-info/METADATA
scrapy_sessions-0.9.dist-info/WHEEL
scrapy_sessions-0.9.dist-info/top_level.txt
scrapy_sessions-0.9.dist-info/RECORD
