Metadata-Version: 2.1
Name: scrapy-sessions
Version: 0.9
Summary: Session management extension for Scrapy.
Home-page: https://github.com/ThomasAitken/scrapy-sessions
Author: Thomas Aitken
Author-email: tclaitken@gmail.com
License: UNKNOWN
Platform: UNKNOWN
Classifier: Programming Language :: Python :: 3
Classifier: Programming Language :: Python :: 3.6
Classifier: Programming Language :: Python :: 3.7
Classifier: Programming Language :: Python :: 3.8
Classifier: Programming Language :: Python :: 3.9
Classifier: License :: OSI Approved :: BSD License
Classifier: Operating System :: OS Independent
